LICENSE
MANIFEST.in
README.md
setup.py
marjoram_org.egg-info/PKG-INFO
marjoram_org.egg-info/SOURCES.txt
marjoram_org.egg-info/dependency_links.txt
marjoram_org.egg-info/top_level.txt
orgapp/__init__.py
orgapp/admin.py
orgapp/urls.py
orgapp/forms/__init__.py
orgapp/forms/contact.py
orgapp/forms/create_organization.py
orgapp/forms/organization.py
orgapp/forms/user_profile.py
orgapp/migrations/0001_initial.py
orgapp/migrations/0002_organization_userprofile.py
orgapp/migrations/0003_auto_20160429_2043.py
orgapp/migrations/0004_auto_20160703_1225.py
orgapp/migrations/__init__.py
orgapp/models/__init__.py
orgapp/models/messages.py
orgapp/models/organization.py
orgapp/models/user.py
orgapp/static/css/bootstrap-theme.css
orgapp/static/css/bootstrap-theme.css.map
orgapp/static/css/bootstrap-theme.min.css
orgapp/static/css/bootstrap-theme.min.css.map
orgapp/static/css/bootstrap.css
orgapp/static/css/bootstrap.css.map
orgapp/static/css/bootstrap.min.css
orgapp/static/css/bootstrap.min.css.map
orgapp/static/css/login.css
orgapp/static/fonts/glyphicons-halflings-regular.eot
orgapp/static/fonts/glyphicons-halflings-regular.svg
orgapp/static/fonts/glyphicons-halflings-regular.ttf
orgapp/static/fonts/glyphicons-halflings-regular.woff
orgapp/static/fonts/glyphicons-halflings-regular.woff2
orgapp/static/js/bootstrap.js
orgapp/static/js/bootstrap.min.js
orgapp/static/js/npm.js
orgapp/static/library/backbone.js
orgapp/static/library/jquery-2.1.3.min.js
orgapp/static/library/jquery.cookie.js
orgapp/static/library/jquery.noty.packaged.min.js
orgapp/static/library/jquery.tooltipster.min.js
orgapp/static/library/jquery.ui.widget.js
orgapp/static/library/underscore.js
orgapp/templates/403.html
orgapp/templates/404.html
orgapp/templates/500.html
orgapp/templates/base.html
orgapp/templates/includes/form_snippet.html
orgapp/templates/includes/search.html
orgapp/templates/includes/volunteer_request_list.html
orgapp/templates/org/contact.html
orgapp/templates/org/create_organization.html
orgapp/templates/org/dashboard.html
orgapp/templates/org/detail.html
orgapp/templates/org/index.html
orgapp/templates/org/organization_detail.html
